astc_decomp_faster.cp39-win_amd64.pyd
astc_decomp_faster-1.1.2.dist-info/LICENSE
astc_decomp_faster-1.1.2.dist-info/METADATA
astc_decomp_faster-1.1.2.dist-info/WHEEL
astc_decomp_faster-1.1.2.dist-info/top_level.txt
astc_decomp_faster-1.1.2.dist-info/RECORD
